django_rest_recaptcha-1.0.2.dist-info/METADATA
django_rest_recaptcha-1.0.2.dist-info/RECORD
django_rest_recaptcha-1.0.2.dist-info/WHEEL
django_rest_recaptcha-1.0.2.dist-info/top_level.txt
recaptcha/__init__.py
recaptcha/constants.py
recaptcha/fields.py
