Metadata-Version: 2.1
Name: django-rest-recaptcha
Version: 1.0.2
Summary: Django rest recaptcha field for easy integration of google recaptcha with django-rest-framework.
Home-page: https://github.com/motius/django-rest-recaptcha
Author: Motius gmbh
Author-email: info@motius.de
License: MIT License
Platform: UNKNOWN
Classifier: Environment :: Web Environment
Classifier: Framework :: Django
Classifier: Framework :: Django :: 1.11
Classifier: Framework :: Django :: 1.10
Classifier: Framework :: Django :: 1.9
Classifier: Framework :: Django :: 1.8
Classifier: Intended Audience :: Developers
Classifier: License :: OSI Approved :: MIT License
Classifier: Operating System :: OS Independent
Classifier: Programming Language :: Python
Classifier: Programming Language :: Python :: 3
Classifier: Programming Language :: Python :: 3.4
Classifier: Programming Language :: Python :: 3.5
